bledom/__init__.py
bledom/__main__.py
bledom/device.py
bledom/main.py
bledom/test_days.py
bledom/util.py
bledom-0.0.9.dist-info/LICENSE
bledom-0.0.9.dist-info/METADATA
bledom-0.0.9.dist-info/WHEEL
bledom-0.0.9.dist-info/top_level.txt
bledom-0.0.9.dist-info/RECORD
