Metadata-Version: 2.1
Name: bledom
Version: 0.0.9
Summary: Python library for controlling BLEDOM devices
Home-page: https://github.com/thegreatrazz/pybledom
Author: Raresh Nistor
Author-email: raresh@nistor.email
License: UNKNOWN
Project-URL: Bug Tracker, https://github.com/thegreatrazz/pybledom/issues
Platform: UNKNOWN
Classifier: Programming Language :: Python :: 3
Classifier: License :: OSI Approved :: MIT License
Classifier: Operating System :: OS Independent
Requires-Python: >=3.6
Requires-Dist: bleak (>=0.11.0)
